odoo9_addon_connector_base_product-9.0.1.0.0.99.dev5-py2.7-nspkg.pth
odoo9_addon_connector_base_product-9.0.1.0.0.99.dev5.dist-info/METADATA
odoo9_addon_connector_base_product-9.0.1.0.0.99.dev5.dist-info/RECORD
odoo9_addon_connector_base_product-9.0.1.0.0.99.dev5.dist-info/WHEEL
odoo9_addon_connector_base_product-9.0.1.0.0.99.dev5.dist-info/namespace_packages.txt
odoo9_addon_connector_base_product-9.0.1.0.0.99.dev5.dist-info/top_level.txt
odoo_addons/connector_base_product/__init__.py
odoo_addons/connector_base_product/__openerp__.py
odoo_addons/connector_base_product/i18n/bg.po
odoo_addons/connector_base_product/i18n/ca.po
odoo_addons/connector_base_product/i18n/connector_base_product.pot
odoo_addons/connector_base_product/i18n/de.po
odoo_addons/connector_base_product/i18n/es.po
odoo_addons/connector_base_product/i18n/fr.po
odoo_addons/connector_base_product/i18n/hu.po
odoo_addons/connector_base_product/i18n/it.po
odoo_addons/connector_base_product/i18n/nl.po
odoo_addons/connector_base_product/i18n/pt_BR.po
odoo_addons/connector_base_product/i18n/sl.po
odoo_addons/connector_base_product/i18n/zh_CN.po
odoo_addons/connector_base_product/static/description/icon.png
odoo_addons/connector_base_product/views/product_view.xml
