Metadata-Version: 2.1
Name: odoo9-addon-connector-base-product
Version: 9.0.1.0.0.99.dev5
Summary: Connector Base Product
Home-page: http://odoo-connector.com
Author: Openerp Connector Core Editors, Odoo Community Association (OCA)
Author-email: support@odoo-community.org
License: AGPL-3
Platform: UNKNOWN
Classifier: Programming Language :: Python
Classifier: Framework :: Odoo
Classifier: License :: OSI Approved :: GNU Affero General Public License v3
Requires-Python: ~=2.7
Requires-Dist: odoo9-addon-connector
Requires-Dist: odoo (<9.1a,>=9.0a)
